{
	"backtraceGraph" : 
	{
		"commands" : 
		[
			"install"
		],
		"files" : 
		[
			"vendor/google/absl/abseil-cpp-20230125.3/CMakeLists.txt"
		],
		"nodes" : 
		[
			{
				"file" : 0
			},
			{
				"command" : 0,
				"file" : 0,
				"line" : 182,
				"parent" : 0
			},
			{
				"command" : 0,
				"file" : 0,
				"line" : 192,
				"parent" : 0
			},
			{
				"command" : 0,
				"file" : 0,
				"line" : 205,
				"parent" : 0
			},
			{
				"command" : 0,
				"file" : 0,
				"line" : 210,
				"parent" : 0
			},
			{
				"command" : 0,
				"file" : 0,
				"line" : 235,
				"parent" : 0
			}
		]
	},
	"installers" : 
	[
		{
			"backtrace" : 1,
			"component" : "Unspecified",
			"destination" : "lib/cmake/absl",
			"exportName" : "abslTargets",
			"exportTargets" : 
			[
				{
					"id" : "atomic_hook::@80ce9754922a200ec89e",
					"index" : 0
				},
				{
					"id" : "errno_saver::@80ce9754922a200ec89e",
					"index" : 0
				},
				{
					"id" : "log_severity::@80ce9754922a200ec89e",
					"index" : 89
				},
				{
					"id" : "raw_logging_internal::@80ce9754922a200ec89e",
					"index" : 110
				},
				{
					"id" : "spinlock_wait::@80ce9754922a200ec89e",
					"index" : 112
				},
				{
					"id" : "config::@80ce9754922a200ec89e",
					"index" : 0
				},
				{
					"id" : "dynamic_annotations::@80ce9754922a200ec89e",
					"index" : 0
				},
				{
					"id" : "core_headers::@80ce9754922a200ec89e",
					"index" : 0
				},
				{
					"id" : "malloc_internal::@80ce9754922a200ec89e",
					"index" : 92
				},
				{
					"id" : "base_internal::@80ce9754922a200ec89e",
					"index" : 0
				},
				{
					"id" : "base::@80ce9754922a200ec89e",
					"index" : 31
				},
				{
					"id" : "throw_delegate::@80ce9754922a200ec89e",
					"index" : 122
				},
				{
					"id" : "pretty_function::@80ce9754922a200ec89e",
					"index" : 0
				},
				{
					"id" : "endian::@80ce9754922a200ec89e",
					"index" : 0
				},
				{
					"id" : "scoped_set_env::@80ce9754922a200ec89e",
					"index" : 111
				},
				{
					"id" : "strerror::@80ce9754922a200ec89e",
					"index" : 117
				},
				{
					"id" : "fast_type_id::@80ce9754922a200ec89e",
					"index" : 0
				},
				{
					"id" : "prefetch::@80ce9754922a200ec89e",
					"index" : 0
				},
				{
					"id" : "algorithm::@13665f6d294101618909",
					"index" : 0
				},
				{
					"id" : "algorithm_container::@13665f6d294101618909",
					"index" : 0
				},
				{
					"id" : "cleanup_internal::@901bc63570bf7c612ce0",
					"index" : 0
				},
				{
					"id" : "cleanup::@901bc63570bf7c612ce0",
					"index" : 0
				},
				{
					"id" : "btree::@90ade927eac46ada3208",
					"index" : 0
				},
				{
					"id" : "compressed_tuple::@90ade927eac46ada3208",
					"index" : 0
				},
				{
					"id" : "fixed_array::@90ade927eac46ada3208",
					"index" : 0
				},
				{
					"id" : "inlined_vector_internal::@90ade927eac46ada3208",
					"index" : 0
				},
				{
					"id" : "inlined_vector::@90ade927eac46ada3208",
					"index" : 0
				},
				{
					"id" : "counting_allocator::@90ade927eac46ada3208",
					"index" : 0
				},
				{
					"id" : "flat_hash_map::@90ade927eac46ada3208",
					"index" : 0
				},
				{
					"id" : "flat_hash_set::@90ade927eac46ada3208",
					"index" : 0
				},
				{
					"id" : "node_hash_map::@90ade927eac46ada3208",
					"index" : 0
				},
				{
					"id" : "node_hash_set::@90ade927eac46ada3208",
					"index" : 0
				},
				{
					"id" : "container_memory::@90ade927eac46ada3208",
					"index" : 0
				},
				{
					"id" : "hash_function_defaults::@90ade927eac46ada3208",
					"index" : 0
				},
				{
					"id" : "hash_policy_traits::@90ade927eac46ada3208",
					"index" : 0
				},
				{
					"id" : "common_policy_traits::@90ade927eac46ada3208",
					"index" : 0
				},
				{
					"id" : "hashtablez_sampler::@90ade927eac46ada3208",
					"index" : 69
				},
				{
					"id" : "hashtable_debug::@90ade927eac46ada3208",
					"index" : 0
				},
				{
					"id" : "hashtable_debug_hooks::@90ade927eac46ada3208",
					"index" : 0
				},
				{
					"id" : "node_slot_policy::@90ade927eac46ada3208",
					"index" : 0
				},
				{
					"id" : "raw_hash_map::@90ade927eac46ada3208",
					"index" : 0
				},
				{
					"id" : "container_common::@90ade927eac46ada3208",
					"index" : 0
				},
				{
					"id" : "raw_hash_set::@90ade927eac46ada3208",
					"index" : 109
				},
				{
					"id" : "layout::@90ade927eac46ada3208",
					"index" : 0
				},
				{
					"id" : "crc_cpu_detect::@757c2d58a45246033c1e",
					"index" : 45
				},
				{
					"id" : "crc_internal::@757c2d58a45246033c1e",
					"index" : 46
				},
				{
					"id" : "crc32c::@757c2d58a45246033c1e",
					"index" : 43
				},
				{
					"id" : "non_temporal_arm_intrinsics::@757c2d58a45246033c1e",
					"index" : 0
				},
				{
					"id" : "non_temporal_memcpy::@757c2d58a45246033c1e",
					"index" : 0
				},
				{
					"id" : "crc_cord_state::@757c2d58a45246033c1e",
					"index" : 44
				},
				{
					"id" : "stacktrace::@ef2abfeaa3ba212b4d9d",
					"index" : 113
				},
				{
					"id" : "symbolize::@ef2abfeaa3ba212b4d9d",
					"index" : 120
				},
				{
					"id" : "examine_stack::@ef2abfeaa3ba212b4d9d",
					"index" : 51
				},
				{
					"id" : "failure_signal_handler::@ef2abfeaa3ba212b4d9d",
					"index" : 53
				},
				{
					"id" : "debugging_internal::@ef2abfeaa3ba212b4d9d",
					"index" : 47
				},
				{
					"id" : "demangle_internal::@ef2abfeaa3ba212b4d9d",
					"index" : 48
				},
				{
					"id" : "leak_check::@ef2abfeaa3ba212b4d9d",
					"index" : 71
				},
				{
					"id" : "debugging::@ef2abfeaa3ba212b4d9d",
					"index" : 0
				},
				{
					"id" : "flags_path_util::@143cff851bfdc07dfd21",
					"index" : 0
				},
				{
					"id" : "flags_program_name::@143cff851bfdc07dfd21",
					"index" : 62
				},
				{
					"id" : "flags_config::@143cff851bfdc07dfd21",
					"index" : 57
				},
				{
					"id" : "flags_marshalling::@143cff851bfdc07dfd21",
					"index" : 59
				},
				{
					"id" : "flags_commandlineflag_internal::@143cff851bfdc07dfd21",
					"index" : 56
				},
				{
					"id" : "flags_commandlineflag::@143cff851bfdc07dfd21",
					"index" : 55
				},
				{
					"id" : "flags_private_handle_accessor::@143cff851bfdc07dfd21",
					"index" : 61
				},
				{
					"id" : "flags_reflection::@143cff851bfdc07dfd21",
					"index" : 63
				},
				{
					"id" : "flags_internal::@143cff851bfdc07dfd21",
					"index" : 58
				},
				{
					"id" : "flags::@143cff851bfdc07dfd21",
					"index" : 54
				},
				{
					"id" : "flags_usage_internal::@143cff851bfdc07dfd21",
					"index" : 65
				},
				{
					"id" : "flags_usage::@143cff851bfdc07dfd21",
					"index" : 64
				},
				{
					"id" : "flags_parse::@143cff851bfdc07dfd21",
					"index" : 60
				},
				{
					"id" : "any_invocable::@c7436cd0a57fa99b54a6",
					"index" : 0
				},
				{
					"id" : "bind_front::@c7436cd0a57fa99b54a6",
					"index" : 0
				},
				{
					"id" : "function_ref::@c7436cd0a57fa99b54a6",
					"index" : 0
				},
				{
					"id" : "hash::@8390b0cbf76956b13b2f",
					"index" : 67
				},
				{
					"id" : "city::@8390b0cbf76956b13b2f",
					"index" : 34
				},
				{
					"id" : "low_level_hash::@8390b0cbf76956b13b2f",
					"index" : 91
				},
				{
					"id" : "log_internal_check_impl::@38f96a287f6d823db583",
					"index" : 0
				},
				{
					"id" : "log_internal_check_op::@38f96a287f6d823db583",
					"index" : 81
				},
				{
					"id" : "log_internal_conditions::@38f96a287f6d823db583",
					"index" : 82
				},
				{
					"id" : "log_internal_config::@38f96a287f6d823db583",
					"index" : 0
				},
				{
					"id" : "log_internal_flags::@38f96a287f6d823db583",
					"index" : 0
				},
				{
					"id" : "log_internal_format::@38f96a287f6d823db583",
					"index" : 83
				},
				{
					"id" : "log_internal_globals::@38f96a287f6d823db583",
					"index" : 84
				},
				{
					"id" : "log_internal_log_impl::@38f96a287f6d823db583",
					"index" : 0
				},
				{
					"id" : "log_internal_proto::@38f96a287f6d823db583",
					"index" : 88
				},
				{
					"id" : "log_internal_message::@38f96a287f6d823db583",
					"index" : 86
				},
				{
					"id" : "log_internal_log_sink_set::@38f96a287f6d823db583",
					"index" : 85
				},
				{
					"id" : "log_internal_nullguard::@38f96a287f6d823db583",
					"index" : 87
				},
				{
					"id" : "log_internal_nullstream::@38f96a287f6d823db583",
					"index" : 0
				},
				{
					"id" : "log_internal_strip::@38f96a287f6d823db583",
					"index" : 0
				},
				{
					"id" : "log_internal_voidify::@38f96a287f6d823db583",
					"index" : 0
				},
				{
					"id" : "log_internal_append_truncated::@38f96a287f6d823db583",
					"index" : 0
				},
				{
					"id" : "absl_check::@38f96a287f6d823db583",
					"index" : 0
				},
				{
					"id" : "absl_log::@38f96a287f6d823db583",
					"index" : 0
				},
				{
					"id" : "check::@38f96a287f6d823db583",
					"index" : 0
				},
				{
					"id" : "die_if_null::@38f96a287f6d823db583",
					"index" : 50
				},
				{
					"id" : "log_flags::@38f96a287f6d823db583",
					"index" : 78
				},
				{
					"id" : "log_globals::@38f96a287f6d823db583",
					"index" : 79
				},
				{
					"id" : "log_initialize::@38f96a287f6d823db583",
					"index" : 80
				},
				{
					"id" : "log::@38f96a287f6d823db583",
					"index" : 0
				},
				{
					"id" : "log_entry::@38f96a287f6d823db583",
					"index" : 77
				},
				{
					"id" : "log_sink::@38f96a287f6d823db583",
					"index" : 90
				},
				{
					"id" : "log_sink_registry::@38f96a287f6d823db583",
					"index" : 0
				},
				{
					"id" : "log_streamer::@38f96a287f6d823db583",
					"index" : 0
				},
				{
					"id" : "log_internal_structured::@38f96a287f6d823db583",
					"index" : 0
				},
				{
					"id" : "log_structured::@38f96a287f6d823db583",
					"index" : 0
				},
				{
					"id" : "memory::@61078594c88e6bd337b7",
					"index" : 0
				},
				{
					"id" : "type_traits::@7dc5ccaf7e9781a34d56",
					"index" : 0
				},
				{
					"id" : "meta::@7dc5ccaf7e9781a34d56",
					"index" : 0
				},
				{
					"id" : "bits::@2654b98585fe5e76f853",
					"index" : 0
				},
				{
					"id" : "int128::@2654b98585fe5e76f853",
					"index" : 70
				},
				{
					"id" : "numeric::@2654b98585fe5e76f853",
					"index" : 0
				},
				{
					"id" : "numeric_representation::@2654b98585fe5e76f853",
					"index" : 0
				},
				{
					"id" : "sample_recorder::@16b598ded5d9cb656581",
					"index" : 0
				},
				{
					"id" : "exponential_biased::@16b598ded5d9cb656581",
					"index" : 52
				},
				{
					"id" : "periodic_sampler::@16b598ded5d9cb656581",
					"index" : 96
				},
				{
					"id" : "random_random::@b00371e1fc900c0a7494",
					"index" : 0
				},
				{
					"id" : "random_bit_gen_ref::@b00371e1fc900c0a7494",
					"index" : 0
				},
				{
					"id" : "random_internal_mock_helpers::@b00371e1fc900c0a7494",
					"index" : 0
				},
				{
					"id" : "random_distributions::@b00371e1fc900c0a7494",
					"index" : 98
				},
				{
					"id" : "random_seed_gen_exception::@b00371e1fc900c0a7494",
					"index" : 107
				},
				{
					"id" : "random_seed_sequences::@b00371e1fc900c0a7494",
					"index" : 108
				},
				{
					"id" : "random_internal_traits::@b00371e1fc900c0a7494",
					"index" : 0
				},
				{
					"id" : "random_internal_distribution_caller::@b00371e1fc900c0a7494",
					"index" : 0
				},
				{
					"id" : "random_internal_fast_uniform_bits::@b00371e1fc900c0a7494",
					"index" : 0
				},
				{
					"id" : "random_internal_seed_material::@b00371e1fc900c0a7494",
					"index" : 106
				},
				{
					"id" : "random_internal_pool_urbg::@b00371e1fc900c0a7494",
					"index" : 101
				},
				{
					"id" : "random_internal_salted_seed_seq::@b00371e1fc900c0a7494",
					"index" : 0
				},
				{
					"id" : "random_internal_iostream_state_saver::@b00371e1fc900c0a7494",
					"index" : 0
				},
				{
					"id" : "random_internal_generate_real::@b00371e1fc900c0a7494",
					"index" : 0
				},
				{
					"id" : "random_internal_wide_multiply::@b00371e1fc900c0a7494",
					"index" : 0
				},
				{
					"id" : "random_internal_fastmath::@b00371e1fc900c0a7494",
					"index" : 0
				},
				{
					"id" : "random_internal_nonsecure_base::@b00371e1fc900c0a7494",
					"index" : 0
				},
				{
					"id" : "random_internal_pcg_engine::@b00371e1fc900c0a7494",
					"index" : 0
				},
				{
					"id" : "random_internal_randen_engine::@b00371e1fc900c0a7494",
					"index" : 0
				},
				{
					"id" : "random_internal_platform::@b00371e1fc900c0a7494",
					"index" : 100
				},
				{
					"id" : "random_internal_randen::@b00371e1fc900c0a7494",
					"index" : 102
				},
				{
					"id" : "random_internal_randen_slow::@b00371e1fc900c0a7494",
					"index" : 105
				},
				{
					"id" : "random_internal_randen_hwaes::@b00371e1fc900c0a7494",
					"index" : 103
				},
				{
					"id" : "random_internal_randen_hwaes_impl::@b00371e1fc900c0a7494",
					"index" : 104
				},
				{
					"id" : "random_internal_distribution_test_util::@b00371e1fc900c0a7494",
					"index" : 99
				},
				{
					"id" : "random_internal_uniform_helper::@b00371e1fc900c0a7494",
					"index" : 0
				},
				{
					"id" : "status::@8f4a12c00c118d7945ea",
					"index" : 114
				},
				{
					"id" : "statusor::@8f4a12c00c118d7945ea",
					"index" : 115
				},
				{
					"id" : "strings::@7007414704b05594cc6d",
					"index" : 118
				},
				{
					"id" : "strings_internal::@7007414704b05594cc6d",
					"index" : 119
				},
				{
					"id" : "str_format::@7007414704b05594cc6d",
					"index" : 0
				},
				{
					"id" : "str_format_internal::@7007414704b05594cc6d",
					"index" : 116
				},
				{
					"id" : "cord_internal::@7007414704b05594cc6d",
					"index" : 38
				},
				{
					"id" : "cordz_update_tracker::@7007414704b05594cc6d",
					"index" : 0
				},
				{
					"id" : "cordz_functions::@7007414704b05594cc6d",
					"index" : 39
				},
				{
					"id" : "cordz_statistics::@7007414704b05594cc6d",
					"index" : 0
				},
				{
					"id" : "cordz_handle::@7007414704b05594cc6d",
					"index" : 40
				},
				{
					"id" : "cordz_info::@7007414704b05594cc6d",
					"index" : 41
				},
				{
					"id" : "cordz_sample_token::@7007414704b05594cc6d",
					"index" : 42
				},
				{
					"id" : "cordz_update_scope::@7007414704b05594cc6d",
					"index" : 0
				},
				{
					"id" : "cord::@7007414704b05594cc6d",
					"index" : 37
				},
				{
					"id" : "graphcycles_internal::@aa970bfc87ec0fce140a",
					"index" : 66
				},
				{
					"id" : "kernel_timeout_internal::@aa970bfc87ec0fce140a",
					"index" : 0
				},
				{
					"id" : "synchronization::@aa970bfc87ec0fce140a",
					"index" : 121
				},
				{
					"id" : "time::@81639d638287bac054fc",
					"index" : 123
				},
				{
					"id" : "civil_time::@81639d638287bac054fc",
					"index" : 35
				},
				{
					"id" : "time_zone::@81639d638287bac054fc",
					"index" : 124
				},
				{
					"id" : "any::@d538e378c980ae3c6822",
					"index" : 0
				},
				{
					"id" : "bad_any_cast::@d538e378c980ae3c6822",
					"index" : 0
				},
				{
					"id" : "bad_any_cast_impl::@d538e378c980ae3c6822",
					"index" : 28
				},
				{
					"id" : "span::@d538e378c980ae3c6822",
					"index" : 0
				},
				{
					"id" : "optional::@d538e378c980ae3c6822",
					"index" : 0
				},
				{
					"id" : "bad_optional_access::@d538e378c980ae3c6822",
					"index" : 29
				},
				{
					"id" : "bad_variant_access::@d538e378c980ae3c6822",
					"index" : 30
				},
				{
					"id" : "variant::@d538e378c980ae3c6822",
					"index" : 0
				},
				{
					"id" : "compare::@d538e378c980ae3c6822",
					"index" : 0
				},
				{
					"id" : "utility::@c7842c6acf3d35847d5a",
					"index" : 0
				}
			],
			"paths" : 
			[
				"vendor/google/protocolbuffers/protobuf-23.3/third_party/abseil-cpp/CMakeFiles/Export/e85e24066b3e116917fcd0763656dbe9/abslTargets.cmake"
			],
			"type" : "export"
		},
		{
			"backtrace" : 2,
			"component" : "Unspecified",
			"destination" : "lib/cmake/absl",
			"paths" : 
			[
				"cmake-build-debug/vendor/google/protocolbuffers/protobuf-23.3/third_party/abseil-cpp/abslConfig.cmake"
			],
			"type" : "file"
		},
		{
			"backtrace" : 3,
			"component" : "Unspecified",
			"destination" : "lib/cmake/absl",
			"paths" : 
			[
				"cmake-build-debug/vendor/google/protocolbuffers/protobuf-23.3/third_party/abseil-cpp/abslConfigVersion.cmake"
			],
			"type" : "file"
		},
		{
			"backtrace" : 4,
			"component" : "Unspecified",
			"destination" : "include",
			"paths" : 
			[
				"vendor/google/absl/abseil-cpp-20230125.3/absl"
			],
			"type" : "directory"
		},
		{
			"backtrace" : 5,
			"component" : "Unspecified",
			"destination" : "include/absl/base",
			"paths" : 
			[
				{
					"from" : "cmake-build-debug/options-pinned.h",
					"to" : "options.h"
				}
			],
			"type" : "file"
		}
	],
	"paths" : 
	{
		"build" : "vendor/google/protocolbuffers/protobuf-23.3/third_party/abseil-cpp",
		"source" : "vendor/google/absl/abseil-cpp-20230125.3"
	}
}
